[
    {
        "title": "Test Title",
        "text": "Test text"
    },
    {
        "title": "Test",
        "text": "New Test",
        "id": "2ad8"
    },
    {
        "title": "Test title 1",
        "text": "Test descriptions\n",
        "id": "eaa5"
    },
    {
        "title": "Test 3",
        "text": "testing testing testing",
        "id": "329e"
    },
    {
        "title": "Test 4",
        "text": "Testing testing\n",
        "id": "40c7"
    },
    {
        "title": "Test 6",
        "text": "Testing testing",
        "id": "4f61"
    }
]